edoc/__init__.py
edoc/main.py
edoc-1.0.1.dist-info/LICENSE
edoc-1.0.1.dist-info/METADATA
edoc-1.0.1.dist-info/WHEEL
edoc-1.0.1.dist-info/top_level.txt
edoc-1.0.1.dist-info/RECORD
